chemometrics/__init__.py
chemometrics/base.py
chemometrics/decomposition.py
chemometrics/plotting.py
chemometrics/preprocessing.py
chemometrics/regression.py
chemometrics/utils.py
chemometrics/mcr/__init__.py
chemometrics/mcr/_constraint.py
chemometrics/mcr/_mcr.py
chemometrics/mcr/_regressor.py
chemometrics/mcr/constraint.py
chemometrics/mcr/metric.py
chemometrics/mcr/regressor.py
chemometrics/mcr/tests/__init__.py
chemometrics/mcr/tests/test_constraint.py
chemometrics/mcr/tests/test_mcr.py
chemometrics/mcr/tests/test_mcr_sklearn_like.py
chemometrics/mcr/tests/test_metric.py
chemometrics/mcr/tests/test_regressor.py
chemometrics/tests/__init__.py
chemometrics/tests/test_base.py
chemometrics/tests/test_decomposition.py
chemometrics/tests/test_plotting.py
chemometrics/tests/test_preprocessing.py
chemometrics/tests/test_regression.py
chemometrics/tests/test_utils.py
chemometrics-0.4.0.dist-info/COPYING
chemometrics-0.4.0.dist-info/METADATA
chemometrics-0.4.0.dist-info/WHEEL
chemometrics-0.4.0.dist-info/top_level.txt
chemometrics-0.4.0.dist-info/RECORD
