Metadata-Version: 2.1
Name: chemometrics
Version: 0.4.0
Summary: package for chemometric data analysis
Home-page: https://github.com/maruedt/chemometrics
Author: Matthias Rüdt
Author-email: mruedt@icloud.com
Classifier: Programming Language :: Python :: 3
Classifier: License :: OSI Approved :: GNU General Public License v3 (GPLv3)
Classifier: Operating System :: OS Independent
Classifier: Topic :: Scientific/Engineering :: Chemistry
Classifier: Topic :: Scientific/Engineering :: Information Analysis
Classifier: Topic :: Scientific/Engineering :: Visualization
Requires-Python: >=3.8
License-File: COPYING
